llmtest/__init__.py
llmtest/core/__init__.py
llmtest/core/assertions.py
llmtest/core/snapshot.py
llmtest/core/test_runner.py
llmtest/metrics/__init__.py
llmtest/metrics/tracker.py
llmtest/optimization/__init__.py
llmtest/optimization/prompt_optimizer.py
llmtest/providers/__init__.py
llmtest/providers/anthropic_provider.py
llmtest/providers/base.py
llmtest/providers/openai_provider.py
llmtest/rag/__init__.py
llmtest/rag/testing.py
llmtest/utils/__init__.py
llmtest/utils/semantic.py
pyllmtest-1.0.1.dist-info/licenses/LICENSE
pyllmtest-1.0.1.dist-info/METADATA
pyllmtest-1.0.1.dist-info/WHEEL
pyllmtest-1.0.1.dist-info/entry_points.txt
pyllmtest-1.0.1.dist-info/top_level.txt
pyllmtest-1.0.1.dist-info/RECORD
