Metadata-Version: 2.4
Name: pyllmtest
Version: 1.0.1
Summary: The most comprehensive LLM testing framework for Python
Home-page: https://github.com/RahulMK22/llmtest
Author: Rahul Malik
Author-email: rm324556@gmail.com
Project-URL: Bug Reports, https://github.com/RahulMK22/llmtest/issues
Project-URL: Source, https://github.com/RahulMK22/llmtest
Project-URL: Documentation, https://llmtest.readthedocs.io
Keywords: llm,testing,ai,openai,anthropic,gpt,claude,pytest,test-automation,quality-assurance,rag,prompt-engineering
Classifier: Development Status :: 4 - Beta
Classifier: Intended Audience :: Developers
Classifier: License :: OSI Approved :: MIT License
Classifier: Programming Language :: Python :: 3
Classifier: Programming Language :: Python :: 3.8
Classifier: Programming Language :: Python :: 3.9
Classifier: Programming Language :: Python :: 3.10
Classifier: Programming Language :: Python :: 3.11
Classifier: Programming Language :: Python :: 3.12
Classifier: Topic :: Software Development :: Testing
Classifier: Topic :: Scientific/Engineering :: Artificial Intelligence
Requires-Python: >=3.8
License-File: LICENSE
Requires-Dist: numpy>=1.20.0
Provides-Extra: openai
Requires-Dist: openai>=1.0.0; extra == "openai"
Requires-Dist: tiktoken>=0.5.0; extra == "openai"
Provides-Extra: anthropic
Requires-Dist: anthropic>=0.18.0; extra == "anthropic"
Provides-Extra: all
Requires-Dist: openai>=1.0.0; extra == "all"
Requires-Dist: tiktoken>=0.5.0; extra == "all"
Requires-Dist: anthropic>=0.18.0; extra == "all"
Requires-Dist: scipy>=1.7.0; extra == "all"
Requires-Dist: scikit-learn>=1.0.0; extra == "all"
Provides-Extra: dev
Requires-Dist: pytest>=7.0.0; extra == "dev"
Requires-Dist: pytest-asyncio>=0.21.0; extra == "dev"
Requires-Dist: black>=22.0.0; extra == "dev"
Requires-Dist: flake8>=4.0.0; extra == "dev"
Requires-Dist: mypy>=0.990; extra == "dev"
Requires-Dist: pytest-cov>=3.0.0; extra == "dev"
Dynamic: author
Dynamic: author-email
Dynamic: classifier
Dynamic: description
Dynamic: description-content-type
Dynamic: home-page
Dynamic: keywords
Dynamic: license-file
Dynamic: project-url
Dynamic: provides-extra
Dynamic: requires-dist
Dynamic: requires-python
Dynamic: summary
